CS/__init__.py
CS/api/Datainput.py
CS/api/Respron.py
CS/api/Storage.py
CS/api/__init__.py
CS/api/__main__.py
CS/api/config.py
CS/api/connect_Database.py
CS/api/model.py
CS/api/utils.py
CS/database/UI.py
CS/database/__init__.py
CS/database/__main__.py
CS/database/config.py
CS/database/database.py
CS/database/model.py
CS/database/service.py
Promotion/Excel_Time.py
Promotion/Format_Product.py
Promotion/Format_excel.py
Promotion/__init__.py
Promotion/__main__.py
Promotion/config.py
Promotion/data_sync_manager.py
Promotion/main_app.py
Promotion/merge_file.py
Promotion/models.py
Promotion/ui.py
Promotion/utils.py
Promotion_Counter/__init__.py
Promotion_Counter/__main__.py
Promotion_Counter/backup_manager.py
Promotion_Counter/config_manager.py
Promotion_Counter/data_mapper.py
Promotion_Counter/database_manager.py
Promotion_Counter/excel_processor.py
Promotion_Counter/file_manager.py
Promotion_Counter/flow_controller.py
Promotion_Counter/log_manager.py
Promotion_Counter/product_manager.py
Promotion_Counter/report_manager.py
Promotion_Counter/utils.py
Promotion_Counter/vnc_manager.py
qcprogs-0.0.5.dist-info/licenses/LICENSE
qcprogs-0.0.5.dist-info/METADATA
qcprogs-0.0.5.dist-info/WHEEL
qcprogs-0.0.5.dist-info/entry_points.txt
qcprogs-0.0.5.dist-info/top_level.txt
qcprogs-0.0.5.dist-info/RECORD
