Metadata-Version: 2.4
Name: QCPROGS
Version: 0.0.5
Summary: QCPROGS is a comprehensive automated solution designed to streamline Excel
Author: surapatsue
Author-email: nakarinsue@outlook.com
Maintainer: nakarinsue
Maintainer-email: nakarinsue@gosoft.co.th
Classifier: Programming Language :: Python :: 3
Classifier: Operating System :: OS Independent
Classifier: Development Status :: 4 - Beta
Classifier: Intended Audience :: Developers
Classifier: Topic :: Software Development :: Libraries
Requires-Python: >=3.9
License-File: LICENSE
Requires-Dist: SQLAlchemy==2.0.41
Requires-Dist: pyodbc==5.2.0
Requires-Dist: openpyxl==3.1.5
Requires-Dist: pandas==2.3.0
Requires-Dist: pillow==11.3.0
Requires-Dist: watchdog==4.0.0
Requires-Dist: requests==2.32.4
Requires-Dist: tqdm==4.66.4
Requires-Dist: icecream==2.1.8
Requires-Dist: matplotlib==3.10.7
Requires-Dist: PyQt6==6.10.0
Requires-Dist: oracledb==3.4.0
Requires-Dist: flet[all]
Dynamic: author
Dynamic: author-email
Dynamic: classifier
Dynamic: description
Dynamic: description-content-type
Dynamic: license-file
Dynamic: maintainer
Dynamic: maintainer-email
Dynamic: requires-dist
Dynamic: requires-python
Dynamic: summary
